openrouterfreescanner/__init__.py
openrouterfreescanner/main.py
openrouterfreescanner/test.py
openrouterfreescanner-1.0.1.dist-info/licenses/LICENSE
openrouterfreescanner-1.0.1.dist-info/METADATA
openrouterfreescanner-1.0.1.dist-info/WHEEL
openrouterfreescanner-1.0.1.dist-info/entry_points.txt
openrouterfreescanner-1.0.1.dist-info/top_level.txt
openrouterfreescanner-1.0.1.dist-info/RECORD
