Metadata-Version: 2.4
Name: openrouterfreescanner
Version: 1.0.1
Summary: CLI and programmatically fetcher for open router current free models with advanced filtering.
Home-page: https://github.com/yourusername/openrouter-free-scanner
Author: Your Name
Author-email: tcsenpai <tcsenpai@discus.sh>
Project-URL: Homepage, https://github.com/tcsenpai/openrouter-free-scanner
Project-URL: Bug Tracker, https://github.com/tcsenpai/openrouter-free-scanner/issues
Classifier: Programming Language :: Python :: 3
Classifier: License :: OSI Approved :: MIT License
Classifier: Operating System :: OS Independent
Requires-Python: >=3.6
License-File: LICENSE
Dynamic: author
Dynamic: home-page
Dynamic: license-file
Dynamic: requires-python
